README.rst
flask_elasticutils.py
setup.py
Flask_ElasticUtils.egg-info/PKG-INFO
Flask_ElasticUtils.egg-info/SOURCES.txt
Flask_ElasticUtils.egg-info/dependency_links.txt
Flask_ElasticUtils.egg-info/not-zip-safe
Flask_ElasticUtils.egg-info/requires.txt
Flask_ElasticUtils.egg-info/top_level.txt