Metadata-Version: 1.1
Name: Flask-ElasticUtils
Version: 0.1.7
Summary: ElasticUtils for Flask
Home-page: https://github.com/neilalbrock/flask-elasticutils/
Author: Neil Albrock - Atomised
Author-email: neil@atomised.coop
License: BSD
Platform: any
Classifier: Environment :: Web Environment
Classifier: Intended Audience :: Developers
Classifier: License :: OSI Approved :: BSD License
Classifier: Operating System :: OS Independent
Classifier: Programming Language :: Python
Classifier: Topic :: Internet :: WWW/HTTP :: Dynamic Content
Classifier: Topic :: Software Development :: Libraries :: Python Modules
